ProxyToolKit/Exceptions.py
ProxyToolKit/Proxy.py
ProxyToolKit/__init__.py
ProxyToolKit/agents.py
ProxyToolKit-2.1.0.dist-info/LICENSE
ProxyToolKit-2.1.0.dist-info/METADATA
ProxyToolKit-2.1.0.dist-info/WHEEL
ProxyToolKit-2.1.0.dist-info/top_level.txt
ProxyToolKit-2.1.0.dist-info/RECORD
