Metadata-Version: 2.1
Name: ProxyToolKit
Version: 2.1.0
Summary: Proxy Scraper and Checker
Home-page: https://github.com/codingwithdevil/ProxyToolKit.git
Author: Coding With Devil ( Binshan Iqbal )
Author-email: codingwithdevil@gmail.com
License: MIT
Classifier: Programming Language :: Python :: 3
Classifier: License :: OSI Approved :: MIT License
Classifier: Operating System :: OS Independent
Requires-Python: >=3.7
License-File: LICENSE
Requires-Dist: beautifulsoup4
Requires-Dist: bs4
Requires-Dist: certifi
Requires-Dist: charset-normalizer
Requires-Dist: idna
Requires-Dist: PySocks
Requires-Dist: requests
Requires-Dist: soupsieve
Requires-Dist: urllib3
